CHANGES.txt
CONTRIBUTORS.txt
MANIFEST.in
README.txt
setup.py
c2/__init__.py
c2.recipe.bitbucketbk.egg-info/PKG-INFO
c2.recipe.bitbucketbk.egg-info/SOURCES.txt
c2.recipe.bitbucketbk.egg-info/dependency_links.txt
c2.recipe.bitbucketbk.egg-info/entry_points.txt
c2.recipe.bitbucketbk.egg-info/namespace_packages.txt
c2.recipe.bitbucketbk.egg-info/not-zip-safe
c2.recipe.bitbucketbk.egg-info/requires.txt
c2.recipe.bitbucketbk.egg-info/top_level.txt
c2/recipe/__init__.py
c2/recipe/bitbucketbk/README.txt
c2/recipe/bitbucketbk/__init__.py
c2/recipe/bitbucketbk/backuprunner.py
c2/recipe/bitbucketbk/tests/__init__.py
c2/recipe/bitbucketbk/tests/test_docs.py