Metadata-Version: 1.0
Name: c2.recipe.bitbucketbk
Version: 1.0b1
Summary: This package is backupp repository from bitbucket.org
Home-page: http://www.cmscom.jp
Author: Manabu TERADA
Author-email: terada@cmscom.jp
License: ZPL
Keywords: bitbucket backup
Platform: UNKNOWN
Classifier: Framework :: Buildout
Classifier: Intended Audience :: Developers
Classifier: Topic :: Software Development :: Build Tools
Classifier: License :: OSI Approved :: Zope Public License
